{"data":[{"titles":[{"type":"Default","title":"Shenqi Du Shan Yu"},{"type":"Japanese","title":"神奇独山玉"}]},{"titles":[{"type":"Default","title":"Weiyu Ye Fengkuang"},{"type":"Japanese","title":"卫浴也疯狂"}]},{"titles":[{"type":"Default","title":"Titi He Kiki: Moli Ketang"},{"type":"Japanese","title":"踢踢和奇奇之魔力课堂"}]},{"titles":[{"type":"Default","title":"Huangdi Shishi"},{"type":"Japanese","title":"黄帝史诗"}]},{"titles":[{"type":"Default","title":"Tutu Zhi Zhen Jia Gongzhu"},{"type":"Japanese","title":"兔兔之真假公主"}]},{"titles":[{"type":"Default","title":"Tutu Zhi Shenqi Mogu"},{"type":"Japanese","title":"兔兔之神奇蘑菇"}]},{"titles":[{"type":"Default","title":"Menghuan Zhuangyuan"},{"type":"Japanese","title":"梦幻庄园"}]},{"titles":[{"type":"Default","title":"Xingji Xiao Mayi: Gongyi Dashi"},{"type":"Japanese","title":"星际小蚂蚁之公益大使"}]},{"titles":[{"type":"Default","title":"Rang Mengxiang Qifei"},{"type":"Japanese","title":"让梦想起飞"}]},{"titles":[{"type":"Default","title":"Mala Xiao Yuanjia"},{"type":"Japanese","title":"麻辣小冤家"}]},{"titles":[{"type":"Default","title":"Xiao Feiji Kaka"},{"type":"Japanese","title":"小飞机卡卡"},{"type":"English","title":"Plane Buddies"}]},{"titles":[{"type":"Default","title":"Jisu Liu Kong Qiu"},{"type":"Japanese","title":"极速六孔球"}]},{"titles":[{"type":"Default","title":"Shaonian Caocao"},{"type":"Japanese","title":"少年曹操"}]},{"titles":[{"type":"Default","title":"Xingxing Meng"},{"type":"Japanese","title":"星星梦"}]},{"titles":[{"type":"Default","title":"Geng Cun Minjian Gushi"},{"type":"Japanese","title":"耿村民间故事"}]},{"titles":[{"type":"Default","title":"Chao Neng Xing: Shikong Yingxiong"},{"type":"Japanese","title":"超能星之时空英雄"}]},{"titles":[{"type":"Default","title":"Peng Peng De Shijie"},{"type":"Japanese","title":"朋朋的世界"}]},{"titles":[{"type":"Default","title":"Xia Xiao Dou"},{"type":"Japanese","title":"夏小兜"}]},{"titles":[{"type":"Default","title":"Papa Mama Xiaoshihou De Gushi"},{"type":"Japanese","title":"爸爸妈妈小时候的故事"}]},{"titles":[{"type":"Default","title":"You Er Gushi Dawang"},{"type":"Japanese","title":"幼儿故事大王"}]},{"titles":[{"type":"Default","title":"Xiao Xiao Dou Leyuan"},{"type":"Japanese","title":"小小逗乐园"}]},{"titles":[{"type":"Default","title":"Yukuai de Shiwumen"},{"type":"Japanese","title":"愉快的食物们"}]},{"titles":[{"type":"Default","title":"Chun Chun Chengzhang Ji: Qingchunqi Pian"},{"type":"Japanese","title":"春春成长记之青春期篇"}]},{"titles":[{"type":"Default","title":"Chun Chun Chengzhang Ji: Fangzhi Ertong Yiwai Pian"},{"type":"Japanese","title":"春春成长记之防止儿童意外篇"}]},{"titles":[{"type":"Default","title":"Lan Se Julebu"},{"type":"Synonym","title":"Skyblue Club"},{"type":"Japanese","title":"蓝色俱乐部"}]}],"pagination":{"has_next_page":true}}