{"data":[{"titles":[{"type":"Default","title":"Yumekui Merry"},{"type":"Synonym","title":"Yumekui Merry"},{"type":"Japanese","title":"夢喰いメリー"},{"type":"English","title":"Dream Eater Merry"}]},{"titles":[{"type":"Default","title":".hack//Quantum"},{"type":"Japanese","title":".hack//Quantum"}]},{"titles":[{"type":"Default","title":"Koi☆Sento"},{"type":"Synonym","title":"Koi☆Cent"},{"type":"Synonym","title":"Koisento"},{"type":"Japanese","title":"コイ☆セント"},{"type":"English","title":"Coicent"}]},{"titles":[{"type":"Default","title":"Mecha☆Afro-kun"},{"type":"Japanese","title":"メカ☆アフロくん"},{"type":"English","title":"Mecha Afro-kun"}]},{"titles":[{"type":"Default","title":"Megane na Kanojo"},{"type":"Synonym","title":"Gankyou na Kanojo"},{"type":"Synonym","title":"Glasses Girlfriends"},{"type":"Japanese","title":"眼鏡なカノジョ"}]},{"titles":[{"type":"Default","title":"Mayo Elle Otokonoko"},{"type":"Synonym","title":"Mayo Elle Otoko no Ko"},{"type":"Japanese","title":"迷elleオトコノ娘"}]},{"titles":[{"type":"Default","title":"Ore no Sora Keiji-hen"},{"type":"Japanese","title":"俺の空 刑事篇"}]},{"titles":[{"type":"Default","title":"Kuma no Gakkou: Jackie to Katie"},{"type":"Synonym","title":"The Bears' School"},{"type":"Japanese","title":"くまのがっこう ～ジャッキーとケイティ～"}]},{"titles":[{"type":"Default","title":"Cheburashka"},{"type":"Japanese","title":"チェブラーシカ"},{"type":"German","title":"Cheburashka und seine Freunde"},{"type":"French","title":"Cheburashka \u0026 Ses Amis"}]},{"titles":[{"type":"Default","title":"Try Z"},{"type":"Japanese","title":"トライゼット"}]},{"titles":[{"type":"Default","title":"Twinkle Nora Rock Me!"},{"type":"Japanese","title":"トゥインクル NORA(ノーラ) ロック・ミー!"}]},{"titles":[{"type":"Default","title":"Bousou Sengokushi"},{"type":"Synonym","title":"Spectre"},{"type":"Synonym","title":"Hosai Sengoku Shi Spectre/Requiem"},{"type":"Synonym","title":"Hosai Sengoku Shi Spectre"},{"type":"Synonym","title":"Hosai Sengoku Shi Requiem"},{"type":"Synonym","title":"Racing Civil War Chronicle Spectre/Requiem"},{"type":"Synonym","title":"Racing Civil War Chronicle Spectre"},{"type":"Synonym","title":"Racing Civil War Chronicle Requiem"},{"type":"Synonym","title":"Bousou Sengokushi: Spectre Tanjou"},{"type":"Japanese","title":"暴走戦國史"}]},{"titles":[{"type":"Default","title":"Torajima no Miime"},{"type":"Synonym","title":"Torajima no Mime"},{"type":"Synonym","title":"Mii the Tabby"},{"type":"Synonym","title":"Miime the Tabby"},{"type":"Japanese","title":"トラジマのミーめ"}]},{"titles":[{"type":"Default","title":"Gakkou no Kowai Uwasa Shin: Hanako-san ga Kita!!"},{"type":"Japanese","title":"学校のｺﾜｲうわさ 新・花子さんがきた!!"}]},{"titles":[{"type":"Default","title":"Battle Spirits: Brave"},{"type":"Synonym","title":"Battlespirits: Brave"},{"type":"Synonym","title":"Battle Spirits Season 3"},{"type":"Japanese","title":"バトルスピリッツ ブレイヴ"}]},{"titles":[{"type":"Default","title":"Fortune Arterial: Akai Yakusoku - Tadoritsuita Basho"},{"type":"Synonym","title":"Fortune Arterial: Akai Yakusoku OVA"},{"type":"Japanese","title":"FORTUNE ARTERIAL 赤い約束 たどり着いた場所"}]},{"titles":[{"type":"Default","title":"Chibi Maruko-chan: Watashi no Suki na Uta"},{"type":"Synonym","title":"Chibi Maruko-chan: My Favorite Song"},{"type":"Japanese","title":"ちびまる子ちゃん わたしの好きな歌"}]},{"titles":[{"type":"Default","title":"Shizukanaru Don: Yakuza Side Story"},{"type":"Synonym","title":"The Quiet Don"},{"type":"Synonym","title":"The Quietened Don"},{"type":"Japanese","title":"静かなるドン Yakuza Side Story"}]},{"titles":[{"type":"Default","title":"Geunyeoneun Yeppeotda"},{"type":"Synonym","title":"She Was Beautiful"},{"type":"Japanese","title":"그녀는 예뻣다"},{"type":"English","title":"Life is Cool"}]},{"titles":[{"type":"Default","title":"Tenshi no Habataki Jun"},{"type":"Synonym","title":"Angel Girl Jun"},{"type":"Japanese","title":"天使のはばたきJUN"}]},{"titles":[{"type":"Default","title":"D.C. I\u0026II P.S.P. Re-Animated"},{"type":"Synonym","title":"Da Capo: D.C. I \u0026 II P.S.P. OVA"},{"type":"Japanese","title":"D.C.I\u0026II P.S.P. RE-ANIMATED"}]},{"titles":[{"type":"Default","title":"Sekirei: Pure Engagement Episode 0"},{"type":"Synonym","title":"Sekirei: Pure Engagement Episode 0"},{"type":"Synonym","title":"Sekirei 2 Special"},{"type":"Synonym","title":"Kanwanidai (Sekirei Shindan/Sekirei Yoka)"},{"type":"Japanese","title":"セキレイ～Pure Engagement～第零羽"}]},{"titles":[{"type":"Default","title":"Cool Cool Bye"},{"type":"Japanese","title":"クール・クール・バイ"}]},{"titles":[{"type":"Default","title":"Molly Star-Racer"},{"type":"Japanese","title":"MOLLY STAR-RACER"}]},{"titles":[{"type":"Default","title":"Hyakka Ryouran: Samurai Girls Specials"},{"type":"Synonym","title":"Hyakka Ryouran ~Otome Ureshi Hazukashi Shoshi no Chigiri~"},{"type":"Synonym","title":"Hyakka Ryouran: Samurai Girls OVA"},{"type":"Japanese","title":"百花繚乱 サムライガールズ 〜乙女♥嬉し恥ずかし将士の契り〜"},{"type":"French","title":"Samurai Girls: 6 Mini-OAV"}]}],"pagination":{"has_next_page":true}}