{"data":[{"titles":[{"type":"Default","title":"Yuujou no Kickoff"},{"type":"Japanese","title":"友情のキックオフ"}]},{"titles":[{"type":"Default","title":"Ningen no Uta"},{"type":"Japanese","title":"にんげんの詩"}]},{"titles":[{"type":"Default","title":"Kizuna: Ningen no Uta Part 2"},{"type":"Japanese","title":"きずな　～にんげんの詩パート２～"}]},{"titles":[{"type":"Default","title":"Mirai Kara no Message"},{"type":"Japanese","title":"未来からのメッセージ"}]},{"titles":[{"type":"Default","title":"Nibiki no Neko to Genkina Kazoku"},{"type":"Synonym","title":"Ni-biki no Neko to Genkina Kazoku"},{"type":"Japanese","title":"二匹の猫と元気な家族"}]},{"titles":[{"type":"Default","title":"Boku no Aozora"},{"type":"Japanese","title":"ぼくの青空"}]},{"titles":[{"type":"Default","title":"Niji no Kakehashi"},{"type":"Japanese","title":"虹のかけ橋"}]},{"titles":[{"type":"Default","title":"Souta no Chikai: Sabetsu ni Makenai Chikara"},{"type":"Japanese","title":"草太の誓い－差別に負けない力－"}]},{"titles":[{"type":"Default","title":"Kumori Nochi Hare"},{"type":"Japanese","title":"くもりのち晴れ"}]},{"titles":[{"type":"Default","title":"Makeruna! Senta: Sayonara Ijime Mushi"},{"type":"Japanese","title":"負けるな！千太～さよならいじめ虫～"}]},{"titles":[{"type":"Default","title":"Mebuki"},{"type":"Japanese","title":"芽吹き"}]},{"titles":[{"type":"Default","title":"Aru Zombie Shoujo no Sainan PV"},{"type":"Synonym","title":"The Misfortune of a Certain Zombie Girl"},{"type":"Japanese","title":"あるゾンビ少女の災難"}]},{"titles":[{"type":"Default","title":"Kakusensou"},{"type":"Japanese","title":"核戦争"}]},{"titles":[{"type":"Default","title":"Juuroku Jizou Monogatari: Sensou no Gisei ni Natta Kodomo-tachi"},{"type":"Japanese","title":"十六地蔵物語 ―戦争の犠牲になった子どもたち―"}]},{"titles":[{"type":"Default","title":"Neko wa Ikite Iru"},{"type":"Japanese","title":"猫は生きている"}]},{"titles":[{"type":"Default","title":"DD Hokuto no Ken 2 Ichigo Aji+"},{"type":"Synonym","title":"Hokuto no Ken: Ichigo Aji"},{"type":"Japanese","title":"DD北斗の拳2 イチゴ味+"},{"type":"English","title":"DD Fist of the North Star 2: Strawberry Flavor Plus"},{"type":"German","title":"DD Fist of the North Star: Strawberry Flavor"},{"type":"Spanish","title":"DD First of The North Star Ⅱ: Strawberry Flavor"}]},{"titles":[{"type":"Default","title":"Norasco (TV)"},{"type":"Synonym","title":"Nora Suko (TV)"},{"type":"Japanese","title":"野良スコ"}]},{"titles":[{"type":"Default","title":"Norasco: Cinema Point Card-hen"},{"type":"Synonym","title":"Nora Suko"},{"type":"Japanese","title":"野良スコ「シネマポイントカード」編"}]},{"titles":[{"type":"Default","title":"Nintama Rantarou: Dokutake Onsen no Dan"},{"type":"Japanese","title":"忍たま乱太郎 ドクタケ温泉の段"}]},{"titles":[{"type":"Default","title":"Nintama Rantarou: Ninjutsu Gakuen to Nazo no Onna - Kore wa Jiken da yo! no Dan"},{"type":"Japanese","title":"忍たま乱太郎 忍術学園と謎の女 これは事件だよ〜！の段"}]},{"titles":[{"type":"Default","title":"Inferno Cop Specials"},{"type":"Synonym","title":"Inferno Cop Sequel"},{"type":"Japanese","title":"インフェルノコップ"}]},{"titles":[{"type":"Default","title":"Boku dake ga Inai Machi"},{"type":"Synonym","title":"The Town Where Only I am Missing"},{"type":"Synonym","title":"BokuMachi"},{"type":"Japanese","title":"僕だけがいない街"},{"type":"English","title":"ERASED"},{"type":"German","title":"ERASED - Die Stadt, in der es mich nicht gibt -"},{"type":"Spanish","title":"Desaparecido"},{"type":"French","title":"ERASED"}]},{"titles":[{"type":"Default","title":"Kamisama Minarai: Himitsu no Cocotama"},{"type":"Synonym","title":"Kamisama Minarai: Himitsu no Kokotama"},{"type":"Japanese","title":"かみさまみならい ヒミツのここたま"}]},{"titles":[{"type":"Default","title":"Burenai Ai de"},{"type":"Synonym","title":"With an Unblurred Eye"},{"type":"Synonym","title":"Hatsune Miku: Burenai ai de"},{"type":"Synonym","title":"Burenai Eye de"},{"type":"Japanese","title":"ぶれないアイで"}]},{"titles":[{"type":"Default","title":"Beyblade Burst"},{"type":"Japanese","title":"ベイブレードバースト"}]}],"pagination":{"has_next_page":true}}