{"data":[{"titles":[{"type":"Default","title":"A-Girl"},{"type":"Japanese","title":"A-Girl [エー・ガール]"},{"type":"English","title":"A-Girl"}]},{"titles":[{"type":"Default","title":"Chibi Kero: Kerobouru no Himitsu!?"},{"type":"Japanese","title":"ちびケロ ケロボールの秘密!?"},{"type":"English","title":"Chibi Kero: Secret of the Kero Ball!?"},{"type":"Spanish","title":"."}]},{"titles":[{"type":"Default","title":"Yoku Wakaru Gendai Mahou"},{"type":"Synonym","title":"Modern Magic for Dummies"},{"type":"Synonym","title":"Properly Learned Modern Magic"},{"type":"Synonym","title":"Manageable Modern Magic"},{"type":"Synonym","title":"Modern Magic Made Simple"},{"type":"Japanese","title":"よくわかる現代魔法"},{"type":"Spanish","title":"Yoku Wakaru Gendai Maho"}]},{"titles":[{"type":"Default","title":"Saimin Jutsu The Animation 2nd"},{"type":"Synonym","title":"Saiminjutsu 2"},{"type":"Japanese","title":"催眠術 THE ANIMATION 2nd"}]},{"titles":[{"type":"Default","title":"Yu☆Gi☆Oh! Duel Monsters: Battle City Special"},{"type":"Synonym","title":"Yugioh"},{"type":"Synonym","title":"Yu-Gi-Oh!"},{"type":"Synonym","title":"Yu-Gi-Oh!: Duel Monsters"},{"type":"Synonym","title":"Yugioh: Duel Monsters Battle City Special"},{"type":"Synonym","title":"Yu-Gi-Oh! Duel Monsters Battle City Hen"},{"type":"Japanese","title":"遊☆戯☆王　デュエルモンスターズ"}]},{"titles":[{"type":"Default","title":"Detective Conan Movie 13: The Raven Chaser"},{"type":"Synonym","title":"Meitantei Conan: Shikkoku no Chaser"},{"type":"Synonym","title":"Detective Conan Movie 13"},{"type":"Japanese","title":"名探偵コナン漆黒の追跡者(チェイサー)"},{"type":"English","title":"Detective Conan Movie 13: The Raven Chaser"},{"type":"German","title":"Detektiv Conan Film 13: Der nachtschwarze Jäger"},{"type":"Spanish","title":"Detective Conan Película 13: El Perseguidor Negro"},{"type":"French","title":"Detective Conan Film 13: Le Chasseur Noir de Jais"}]},{"titles":[{"type":"Default","title":"Top wo Nerae! Kagaku Kouza"},{"type":"Synonym","title":"Aim for the Top! Science Lesson"},{"type":"Synonym","title":"Gunbuster! Science Course"},{"type":"Synonym","title":"Top wo Nerae! Kagakukouza"},{"type":"Japanese","title":"トップをねらえ！科学講座"},{"type":"English","title":"Gunbuster! Science Lesson"}]},{"titles":[{"type":"Default","title":"Cafe Junkie"},{"type":"Japanese","title":"カフェ・ジャンキー"}]},{"titles":[{"type":"Default","title":"Mahoutsukai Tai! vs. Shamanic Princess"},{"type":"Synonym","title":"Magic User's Club! vs. Shamanic Princess"},{"type":"Japanese","title":"魔法使いTai! vs シャーマニックプリンセス"}]},{"titles":[{"type":"Default","title":"Yattokame Tanteidan"},{"type":"Synonym","title":"At Last! Turtle Detective Agency"},{"type":"Japanese","title":"やっとかめ探偵団"}]},{"titles":[{"type":"Default","title":"Birthday Boy"},{"type":"Japanese","title":"축생일"}]},{"titles":[{"type":"Default","title":"Kokoro Toshokan: Communication Clips"},{"type":"Synonym","title":"Heart Library: Communication Clips"},{"type":"Japanese","title":"ココロ図書館 - コミュニケーションは切る"}]},{"titles":[{"type":"Default","title":"Tsuri Baka Nisshi"},{"type":"Synonym","title":"Fishing Fool Diary"},{"type":"Synonym","title":"Diary of a Fishing Fool"},{"type":"Japanese","title":"釣りバカ日誌"}]},{"titles":[{"type":"Default","title":"Yobarete Tobidete Akubi-chan"},{"type":"Synonym","title":"Akubi-chan"},{"type":"Japanese","title":"よばれてとびでて！アクビちゃん"}]},{"titles":[{"type":"Default","title":"Time Bokan 2000: Kaitou Kiramekiman"},{"type":"Synonym","title":"Time Boken 2000: Kiramekiman"},{"type":"Synonym","title":"Kaitou Kiramekiman"},{"type":"Synonym","title":"Thief Glittering Man"},{"type":"Japanese","title":"タイムボカン2000 怪盗きらめきマン"}]},{"titles":[{"type":"Default","title":"Fushigi na Melmo"},{"type":"Synonym","title":"Fushigi na Merumo"},{"type":"Synonym","title":"Marvelous Melmo"},{"type":"Japanese","title":"ふしぎなメルモ"},{"type":"English","title":"Marvelous Melmo"}]},{"titles":[{"type":"Default","title":"Gozonji! Gekkou Kamen-kun"},{"type":"Synonym","title":"Moonlight Mask"},{"type":"Synonym","title":"The Familiar Moonlight Mask-kun"},{"type":"Synonym","title":"Little Moonlight Rider"},{"type":"Japanese","title":"ごぞんじ！月光仮面くん"}]},{"titles":[{"type":"Default","title":"Bikkuriman 2000"},{"type":"Japanese","title":"ビックリマン2000"}]},{"titles":[{"type":"Default","title":"Wagaya no Oinari-sama.: Kuu-chan no Omake Gekijou"},{"type":"Synonym","title":"Wagaya no Oinari-sama. Specials"},{"type":"Japanese","title":"我が家のお稲荷さま。 クーちゃんのオマケ劇場"}]},{"titles":[{"type":"Default","title":"Shin Mazinger Shougeki! Z-hen"},{"type":"Synonym","title":"Shin Mazinger Shogeki! Z-hen"},{"type":"Synonym","title":"True Mazinger"},{"type":"Synonym","title":"Z Mazinger"},{"type":"Japanese","title":"Ｚマジンガー; 真マジンガー 衝撃！Z編"},{"type":"English","title":"Mazinger Edition Z: The Impact!"},{"type":"German","title":"Mazinger Edition Z: The Impact!"},{"type":"Spanish","title":"Mazinger Edition Z: The Impact!"},{"type":"French","title":"Mazinger Edition Z: The Impact!"}]},{"titles":[{"type":"Default","title":"Platonic Chain: Web"},{"type":"Synonym","title":"Platonic Chain Special"},{"type":"Japanese","title":"プラトニック・チェーン"}]},{"titles":[{"type":"Default","title":"Ranma ½: Akumu! Shunmin Kou"},{"type":"Synonym","title":"Ranma ½: Okumu! Shunmin Kou"},{"type":"Synonym","title":"Ranma ½: Nightmare! Incense of Spring Sleep"},{"type":"Synonym","title":"It's a Rumic World: Ranma ½"},{"type":"Japanese","title":"らんま1/2 悪夢! 春眠香"}]},{"titles":[{"type":"Default","title":"Konnichiwa Anne: Before Green Gables"},{"type":"Synonym","title":"Anne of Green Gables Prequel"},{"type":"Synonym","title":"Akage no Anne Prequel"},{"type":"Japanese","title":"こんにちは アン ～Before Green Gables"},{"type":"English","title":"Before Green Gables"}]},{"titles":[{"type":"Default","title":"Feng Yun Jue"},{"type":"Synonym","title":"Wind and Cloud Duel"},{"type":"Japanese","title":"風雲決"},{"type":"English","title":"Storm Rider: Clash of the Evils"},{"type":"German","title":"Storm Rider: Clash of Evil"}]},{"titles":[{"type":"Default","title":"Gun x Sword-san"},{"type":"Japanese","title":"ガン×ソードさん"}]}],"pagination":{"has_next_page":true}}