{"data":[{"titles":[{"type":"Default","title":"Menghuan Maomi Wu"},{"type":"Japanese","title":"梦幻猫咪屋"}]},{"titles":[{"type":"Default","title":"Lao Kai de Qihuan Tanxian Zhi Lu"},{"type":"Japanese","title":"老凯的奇幻探险之旅"}]},{"titles":[{"type":"Default","title":"Xi Hang Zongdongyuan: Loulan Chuanqi"},{"type":"Japanese","title":"西行总动员之楼兰传奇"}]},{"titles":[{"type":"Default","title":"Xiong Hai Zi Anquan Xiao Jiangtang"},{"type":"Japanese","title":"熊孩子安全小讲堂"}]},{"titles":[{"type":"Default","title":"Xiong Hai Zi Dizi Gui"},{"type":"Japanese","title":"熊孩子弟子规"}]},{"titles":[{"type":"Default","title":"Xiong Haizi Sanzijing"},{"type":"Japanese","title":"熊孩子三字经"}]},{"titles":[{"type":"Default","title":"Guai Guai Pinyin Lixian Ji"},{"type":"Japanese","title":"怪怪拼音历险记"}]},{"titles":[{"type":"Default","title":"Guai Guai Pinyin Lixian Ji 2nd Season"},{"type":"Japanese","title":"怪怪拼音历险记第二季"}]},{"titles":[{"type":"Default","title":"Bing Ji Chaoren Kuaidi Xia"},{"type":"Synonym","title":"Kuai D Man"},{"type":"Japanese","title":"丙级超人快递侠"}]},{"titles":[{"type":"Default","title":"Bing Ji Chaoren Kuaidi Xia 2nd Season"},{"type":"Japanese","title":"丙级超人快递侠 第二季"}]},{"titles":[{"type":"Default","title":"Kuaidi Xia Waizhuan"},{"type":"Japanese","title":"快递侠外传"}]},{"titles":[{"type":"Default","title":"Menghuan Bu Bu Xing"},{"type":"Synonym","title":"Menghuan BoBo Xing"},{"type":"Japanese","title":"梦幻布布星"}]},{"titles":[{"type":"Default","title":"Happy Fuzi"},{"type":"Synonym","title":"Ha Pi Fuzi"},{"type":"Synonym","title":"Happy Father and Son"},{"type":"Japanese","title":"哈皮父子"},{"type":"English","title":"Happy Father Happy Son"}]},{"titles":[{"type":"Default","title":"Happy Fuzi: Chao Neng Pao Dan"},{"type":"Synonym","title":"Happy Father and Son: Super Bubble Egg"},{"type":"Japanese","title":"哈皮父子之超能泡蛋"}]},{"titles":[{"type":"Default","title":"Happy Fuzi: Yu Shui Jingang"},{"type":"Synonym","title":"Happy Father and Son and Water King Kong"},{"type":"Japanese","title":"哈皮父子与水金刚"}]},{"titles":[{"type":"Default","title":"Muzhi Xiong Kangji"},{"type":"Japanese","title":"拇指熊康吉"}]},{"titles":[{"type":"Default","title":"Heper Yijia"},{"type":"Synonym","title":"Ha Pu Yijia"},{"type":"Japanese","title":"哈普一家"},{"type":"English","title":"The Heper's Family"}]},{"titles":[{"type":"Default","title":"Koushui Liang Shan"},{"type":"Japanese","title":"口水良山"}]},{"titles":[{"type":"Default","title":"Kuaile Dongxi"},{"type":"Japanese","title":"快乐东西"},{"type":"English","title":"Happy Stuff"}]},{"titles":[{"type":"Default","title":"Kuaile Dongxi 2"},{"type":"Japanese","title":"快乐东西2"},{"type":"English","title":"Happy Stuff 2"}]},{"titles":[{"type":"Default","title":"Kuaile Dongxi 3"},{"type":"Japanese","title":"快乐东西3"},{"type":"English","title":"Happy Stuff 3"}]},{"titles":[{"type":"Default","title":"Kuaile Dongxi 4"},{"type":"Japanese","title":"快乐东西4"},{"type":"English","title":"Happy Stuff 4"}]},{"titles":[{"type":"Default","title":"Kuaile Xiao Dongxi"},{"type":"Japanese","title":"快乐小东西"}]},{"titles":[{"type":"Default","title":"Dongxi Chaguan"},{"type":"Japanese","title":"东西茶馆"}]},{"titles":[{"type":"Default","title":"Kuai Yue Jia Nianhua"},{"type":"Synonym","title":"Happy Stuff 5"},{"type":"Synonym","title":"Kuaile Dongxi 5"},{"type":"Japanese","title":"快乐家年华"}]}],"pagination":{"has_next_page":true}}