{"data":[{"titles":[{"type":"Default","title":"Sore Ike! Anpanman: Sing! Dance! Everybody's Christmas"},{"type":"Synonym","title":"Go! Anpanman: Sing! Dance! Everybody's Christmas"},{"type":"Japanese","title":"それいけ!アンパンマン うたおう!おどろう!みんなのクリスマス"}]},{"titles":[{"type":"Default","title":"Yasashii March"},{"type":"Japanese","title":"やさしいマーチ-The Tender March-"},{"type":"English","title":"The Tender March"}]},{"titles":[{"type":"Default","title":"Koukai Benjo The Animation"},{"type":"Synonym","title":"Public Toilet"},{"type":"Japanese","title":"公開便所 THE ANIMATION"}]},{"titles":[{"type":"Default","title":"D.C.III: Da Capo III Special"},{"type":"Japanese","title":"D.C.III～ダ・カーポIII～"}]},{"titles":[{"type":"Default","title":"Choujin Locke Special"},{"type":"Synonym","title":"Locke the Superman Pilot"},{"type":"Japanese","title":"超人ロック"}]},{"titles":[{"type":"Default","title":"Transfer"},{"type":"Japanese","title":"Transfer"}]},{"titles":[{"type":"Default","title":"Monogatari Series: Second Season"},{"type":"Synonym","title":"Nekomonogatari: Shiro"},{"type":"Synonym","title":"Kabukimonogatari"},{"type":"Synonym","title":"Otorimonogatari"},{"type":"Synonym","title":"Onimonogatari"},{"type":"Synonym","title":"Koimonogatari"},{"type":"Japanese","title":"〈物語〉シリーズ セカンドシーズン"},{"type":"English","title":"Monogatari Series: Second Season"},{"type":"French","title":"Monogatari Seconde Saison"}]},{"titles":[{"type":"Default","title":"Chagama Ondo"},{"type":"Synonym","title":"The Dance of the Chagamas"},{"type":"Japanese","title":"茶釜音頭"}]},{"titles":[{"type":"Default","title":"Soukyuu no Fafner: Dead Aggressor - Exodus"},{"type":"Japanese","title":"蒼穹のファフナー Dead Aggressor EXODUS"},{"type":"German","title":"Fafner Exodus"},{"type":"Spanish","title":"Fafner Exodus"},{"type":"French","title":"Fafner Exodus"}]},{"titles":[{"type":"Default","title":"Aiura"},{"type":"Japanese","title":"あいうら"},{"type":"English","title":"Aiura"}]},{"titles":[{"type":"Default","title":"Agigongryong Doolie (1988)"},{"type":"Synonym","title":"Baby Dinosaur Dooly (1988)"},{"type":"Japanese","title":"아기공룡 둘리"},{"type":"English","title":"Little Dino Dooly (1988)"}]},{"titles":[{"type":"Default","title":"Agigongryong Doolie"},{"type":"Synonym","title":"Baby Dinosaur Dooly"},{"type":"Japanese","title":"아기공룡 둘리"},{"type":"English","title":"Little Dino Dooly"}]},{"titles":[{"type":"Default","title":"Agigongryong Doolie (2009)"},{"type":"Japanese","title":"아기공룡 둘리"},{"type":"English","title":"Little Dino Dooly (2009)"}]},{"titles":[{"type":"Default","title":"Dallyeola Hani"},{"type":"Synonym","title":"Run Hany"},{"type":"Japanese","title":"달려라 하니"}]},{"titles":[{"type":"Default","title":"Nae Ireumeun Dokgotak"},{"type":"Japanese","title":"私の名前はDokgo Takです"},{"type":"English","title":"My name is Dokgo Tak"}]},{"titles":[{"type":"Default","title":"Lolling Seutajeu"},{"type":"Japanese","title":"롤링 스타즈"},{"type":"English","title":"Rolling Stars"}]},{"titles":[{"type":"Default","title":"Lolling Seutajeu (Movie)"},{"type":"Japanese","title":"롤링 스타즈"},{"type":"English","title":"Rolling Stars (Movie)"}]},{"titles":[{"type":"Default","title":"Wala! Pyeon-uijeom The Animation"},{"type":"Synonym","title":"Welcome to Convenience Store!"},{"type":"Japanese","title":"와라! 편의점 the animation"},{"type":"English","title":"Welcome to Wara Store!"}]},{"titles":[{"type":"Default","title":"Crayon Shin-chan Movie 21: Bakauma! B-Kyuu Gourmet Survival Battle!!"},{"type":"Japanese","title":"映画クレヨンしんちゃん バカうまっ! B級グルメサバイバル!!"},{"type":"Spanish","title":"Shin Chan Película 21: El Secreto está en la Salsa"}]},{"titles":[{"type":"Default","title":"Pokemon Best Wishes! Season 2: Episode N"},{"type":"Synonym","title":"Pocket Monsters: Best Wishes! 2 - Episode N"},{"type":"Japanese","title":"ポケットモンスター ベストウイッシュ シーズン2 エピソードN"},{"type":"English","title":"Pokémon: Black \u0026 White: Adventures in Unova"},{"type":"German","title":"Pokémon la Série Staffel 16: Noir et Blanc"},{"type":"Spanish","title":"Pokémon Negro Y Blanco Aventuras En Unova Y Más Allá ."},{"type":"French","title":"Pokémon la Série Saison 16: Noir et Blanc"}]},{"titles":[{"type":"Default","title":"Aoi Kioku: Manmou Kaitaku to Shounen-tachi"},{"type":"Japanese","title":"蒼い記憶 満蒙開拓と少年たち"}]},{"titles":[{"type":"Default","title":"Dareka no Manazashi"},{"type":"Japanese","title":"だれかのまなざし"},{"type":"English","title":"Someone's Gaze"}]},{"titles":[{"type":"Default","title":"Chokkyuu Hyoudai Robot Anime: Straight Title"},{"type":"Japanese","title":"直球表題 ロボットアニメ-STRAIGHT TITLE-"},{"type":"English","title":"Straight Title Robot Anime"},{"type":"German","title":"Straight Title Robot Anime"},{"type":"Spanish","title":"Chokkyuu Hyoudai Robot Anime"},{"type":"French","title":"Straight Title Robot Anime"}]},{"titles":[{"type":"Default","title":"Dennou Sentai Voogie's★Angel: Forever and Ever"},{"type":"Japanese","title":"電脳戦隊ヴギィ'ズ★エンジェル FOREVER AND EVER"}]},{"titles":[{"type":"Default","title":"Saiyuuki Gaiden: Kouga no Shou"},{"type":"Synonym","title":"Saiyuki Gaiden: Tokubetsu-hen - Kouga no Shou"},{"type":"Synonym","title":"Saiyuki Gaiden: Fragment Chapter"},{"type":"Japanese","title":"最遊記外伝　特別編　香花の章"}]}],"pagination":{"has_next_page":true}}