{"data":[{"titles":[{"type":"Default","title":"Spy x Family"},{"type":"Japanese","title":"SPY×FAMILY"}]},{"titles":[{"type":"Default","title":"Irodorimidori"},{"type":"Japanese","title":"イロドリミドリ"}]},{"titles":[{"type":"Default","title":"Hua Jianghu: Bu Liang Ren V"},{"type":"Synonym","title":"Painting Rivers and Lakes 5"},{"type":"Synonym","title":"Hua Jiang Hu: Bu Liang Ren 5th Season"},{"type":"Japanese","title":"画江湖之不良人 V"}]},{"titles":[{"type":"Default","title":"Tomodachi Game"},{"type":"Synonym","title":"Friends Game"},{"type":"Japanese","title":"トモダチゲーム"},{"type":"English","title":"Tomodachi Game"}]},{"titles":[{"type":"Default","title":"Yao Shen Ji 5th Season"},{"type":"Synonym","title":"Yao Shen ji 5th Season"},{"type":"Synonym","title":"Tales of Demons and Gods 5th Season"},{"type":"Japanese","title":"妖神记第五季"},{"type":"English","title":"Tales of Demons and Gods Season 5"}]},{"titles":[{"type":"Default","title":"Sword Art Online: Progressive Movie - Kuraki Yuuyami no Scherzo"},{"type":"Japanese","title":"劇場版 ソードアート・オンライン -プログレッシブ- 冥き夕闇のスケルツォ"},{"type":"English","title":"Sword Art Online the Movie: Progressive - Scherzo of Deep Night"}]},{"titles":[{"type":"Default","title":"Jing: Shuang Cheng 2nd Season"},{"type":"Japanese","title":"镜·双城 第二季"},{"type":"English","title":"The Mirror: Twin Cities"}]},{"titles":[{"type":"Default","title":"Delicious Party♡Precure"},{"type":"Japanese","title":"デリシャスパーティ♡プリキュア"},{"type":"English","title":"Delicious Party Pretty Cure"}]},{"titles":[{"type":"Default","title":"Mazica Party Movie"},{"type":"Synonym","title":"Gekijouban Soushuuhen Mazica Party"},{"type":"Japanese","title":"劇場版 総集編 マジカパーティ"}]},{"titles":[{"type":"Default","title":"Technoroid: Overmind"},{"type":"Japanese","title":"テクノロイド OVERMIND"}]},{"titles":[{"type":"Default","title":"On Air Dekinai!"},{"type":"Japanese","title":"オンエアできない!"}]},{"titles":[{"type":"Default","title":"Kyuuketsuki Sugu Shinu 2"},{"type":"Synonym","title":"KyuuShi"},{"type":"Japanese","title":"吸血鬼すぐ死ぬ2"},{"type":"English","title":"The Vampire Dies in No Time Season 2"}]},{"titles":[{"type":"Default","title":"Cinderella"},{"type":"Japanese","title":"シンデレラ"},{"type":"English","title":"Cinderella"}]},{"titles":[{"type":"Default","title":"Rhythmens"},{"type":"Japanese","title":"Rhythmens (리드멘스)"}]},{"titles":[{"type":"Default","title":"Fudanshi Shoukan: Isekai de Shinjuu ni Hameraremashita 2nd Season"},{"type":"Japanese","title":"腐男子召喚〜異世界で神獣にハメられました〜 2nd"}]},{"titles":[{"type":"Default","title":"Slow Starter"}]},{"titles":[{"type":"Default","title":"Shouji Li de Huanxiong Xiao Zhen 2nd Season"},{"type":"Japanese","title":"手机里的浣熊小镇 第二季"},{"type":"English","title":"Raccoon Town in the Phone 2nd Season"}]},{"titles":[{"type":"Default","title":"Ruguo Lishi Shi Yiqun Miao 6th Season"},{"type":"Synonym","title":"History Cats 6th Season"},{"type":"Synonym","title":"When History Meows 6"},{"type":"Japanese","title":"如果历史是一群喵 第6季"}]},{"titles":[{"type":"Default","title":"Ruguo Lishi Shi Yiqun Miao 7th Season"},{"type":"Synonym","title":"History Cats 7th Season"},{"type":"Synonym","title":"When History Meows 7"},{"type":"Japanese","title":"如果历史是一群喵 第七季"}]},{"titles":[{"type":"Default","title":"Bu Bai Chi Hua Shanhai Jing"},{"type":"Japanese","title":"不白吃话山海经"},{"type":"English","title":"Foodie Boy’s Classic of Mountains \u0026 Seas"}]},{"titles":[{"type":"Default","title":"Ashuai 5th Season"},{"type":"Japanese","title":"阿衰 第五季"}]},{"titles":[{"type":"Default","title":"Ashuai 6th Season"},{"type":"Japanese","title":"阿衰 第六季"}]},{"titles":[{"type":"Default","title":"Ji Gong: Xiang Long Jiang Shi"},{"type":"Synonym","title":"Jigong Zhi Xiang Long Jiang Shi"},{"type":"Japanese","title":"济公之降龙降世"},{"type":"English","title":"Master Ji Gong"}]},{"titles":[{"type":"Default","title":"Tunshi Yongheng"},{"type":"Japanese","title":"吞噬永恆"},{"type":"English","title":"Devour Eternity"}]},{"titles":[{"type":"Default","title":"Pupa (Movie)"},{"type":"Japanese","title":"Pupa"}]}],"pagination":{"has_next_page":true}}