{"page":{"media":[{"title":{"english":null,"romaji":"Time Bokan 2000: Kaitou Kiramekiman","native":"タイムボカン2000 怪盗きらめきマン"}},{"title":{"english":null,"romaji":"Fushigi na Melmo","native":"ふしぎなメルモ"}},{"title":{"english":null,"romaji":"Gozonji! Gekkou Kamen-kun","native":"ごぞんじ！月光仮面くん"}},{"title":{"english":null,"romaji":"Bikkuriman 2000","native":"ビックリマン2000"}},{"title":{"english":null,"romaji":"Wagaya no Oinari-sama. Specials","native":"我が家のお稲荷さま。"}},{"title":{"english":"Mazinger Edition Z: The Impact!","romaji":"Shin Mazinger Shougeki! Z-hen","native":"真マジンガー 衝撃！Z編"}},{"title":{"english":null,"romaji":"Platonic Chain: Web","native":null}},{"title":{"english":null,"romaji":"Ranma 1/2: Akumu! Shunmin Kou","native":"らんま1/2 悪夢! 春眠香"}},{"title":{"english":null,"romaji":"Konnichiwa Anne: Before Green Gables","native":"こんにちは アン 〜Before Green Gables"}},{"title":{"english":null,"romaji":"Gun x Sword-san","native":"ガン×ソードさん"}},{"title":{"english":"Atagoal - Cat's Magical Forest","romaji":"Atagoal wa Neko no Mori","native":"アタゴオルは猫の森"}},{"title":{"english":"Polyphonica Crimson S","romaji":"Shinkyoku Soukai Polyphonica crimson S","native":"神曲奏界ポリフォニカcrimsonS"}},{"title":{"english":null,"romaji":"Viper's Creed","native":"ヴァイパーズ・クリード"}},{"title":{"english":"Valkyria Chronicles","romaji":"Senjou no Valkyria: Gallian Chronicles","native":"戦場のヴァルキュリア -Gallian Chronicles-"}},{"title":{"english":"Dangard Ace Movie: The Great Space War","romaji":"Wakusei Robo Danguard Ace: Uchuu Daikaisen","native":"惑星ロボ ダンガードA[エース] 宇宙大海戦"}},{"title":{"english":null,"romaji":"Onegai My Melody Sukkiri♪","native":"おねがい マイメロディ すっきり♪"}},{"title":{"english":null,"romaji":"Hayate no Gotoku!!: Atsu ga Natsuize - Mizugi-hen!","native":"ハヤテのごとく!! アツがナツいぜ 水着編!"}},{"title":{"english":"Dirty by the Dozen","romaji":"Juuninin no Onna Kyoushi","native":"十二人の女教師"}},{"title":{"english":"07-Ghost","romaji":"07-Ghost","native":"セブンゴースト"}},{"title":{"english":"Pokémon: Pikachu's Vacation","romaji":"Pikachu no Natsuyasumi","native":"ピカチュウのなつやすみ"}},{"title":{"english":"Pokémon: Gotta Dance!","romaji":"Odoru Pokémon Himitsu Kichi","native":"おどるポケモンひみつ基地"}},{"title":{"english":null,"romaji":"Pandora Hearts","native":"パンドラハーツ"}},{"title":{"english":null,"romaji":"Hai! Akko Desu","native":"ハーイあっこです"}},{"title":{"english":"Secret of the Seal","romaji":"Tottoi","native":"トトイ"}},{"title":{"english":"Letter Bee: Light and Blue Night Fantasy","romaji":"Tegami Bachi: Hikari to Ao no Gensou Yawa","native":"テガミバチ 〜光と青の幻想夜話〜"}},{"title":{"english":null,"romaji":"Blassreiter Navigator","native":"ブラスレイター・ナビ"}},{"title":{"english":null,"romaji":"Datenshi-tachi no Kyouen","native":"堕天使たちの狂宴 (原作: ダーティ松本)"}},{"title":{"english":null,"romaji":"The Satisfaction","native":null}},{"title":{"english":null,"romaji":"Telepathist AI Q315 Saiko","native":"テレパシスト愛Q315(サイコ)"}},{"title":{"english":null,"romaji":"Under World","native":null}},{"title":{"english":null,"romaji":"Suashi no Houkago","native":"裸足の放課後"}},{"title":{"english":null,"romaji":"Heisei Jogakuen Kagai Lesson","native":"平成女学園 課外レッスン"}},{"title":{"english":null,"romaji":"Ecchi de Happy! Pin! Pin! Pin!","native":"エッチでハッピー!ピン!ピン!ピン!"}},{"title":{"english":null,"romaji":"Kateikyoushi Bishounen Kari","native":"家庭教師　美少年狩り"}},{"title":{"english":null,"romaji":"69 Pink Riders","native":"69ピンクライダース"}},{"title":{"english":"Butt Attack Punisher Girl Gautaman R","romaji":"Dengeki Oshioki Musume Gootaman R: Ai to Kanashimi no Final Battle","native":"臀撃おしおき娘ゴータマンＲ（リターン）～愛と悲しみのファイナルバトル"}},{"title":{"english":null,"romaji":"Fujun Isei Kouyuu: Taisetsu na Kimi e","native":"不純異性交遊 ～大切な君へ～"}},{"title":{"english":null,"romaji":"Shirouto Kurabu","native":"素人倶楽部/ハメ撮りアニメ完全無修正!!"}},{"title":{"english":null,"romaji":"Rebiya","native":"零媚耶"}},{"title":{"english":null,"romaji":"Love Forever","native":"ラブフォーエヴァー"}},{"title":{"english":null,"romaji":"Eguchi Hisashi no NANTOKA NARUDESHO!","native":"江口寿史のNANTOKA NARUDESHO!"}},{"title":{"english":null,"romaji":"Suishou no Yoru: Aoi Kokuhaku yori","native":"水晶の夜 ~蒼い告白より~"}},{"title":{"english":null,"romaji":"Moonlight Sonata","native":"ムーンライトソナタ"}},{"title":{"english":null,"romaji":"Kugutsu Ai: Doura Gaiden","native":"傀儡哀～瞳裸外伝～"}},{"title":{"english":null,"romaji":"Auction: Bijo Dorei","native":"闇市場[オークション] ～美女奴隷～"}},{"title":{"english":null,"romaji":"Nijuusou: Wana ni Ochita Onnatachi","native":"二重奏　~罠に落ちた女たち~"}},{"title":{"english":null,"romaji":"Aoi Kokuhaku","native":"蒼い告白"}},{"title":{"english":null,"romaji":"Police Girl Yayoi","native":null}},{"title":{"english":null,"romaji":"Chounouryoku Shoujo Barabanba","native":"超能力少女バラバンバ"}},{"title":{"english":null,"romaji":"Age Man to Fuku Chin","native":"あげまんと福ちん"}}],"pageInfo":{"hasNextPage":true}}}